README.md
setup.py
psuedologger/__init__.py
psuedologger/psuedologger.py
psuedologger.egg-info/PKG-INFO
psuedologger.egg-info/SOURCES.txt
psuedologger.egg-info/dependency_links.txt
psuedologger.egg-info/top_level.txt