Metadata-Version: 2.1
Name: psuedologger
Version: 0.0.1
Summary: Simple logger replacement, can be replaced in a program the true Python logger.
Home-page: https://github.com/StephenMal/psuedologger
Author: Stephen Maldonado
Author-email: psuedologger@stephenmal.com
License: UNKNOWN
Platform: UNKNOWN
Classifier: Development Status :: 1 - Planning
Classifier: Programming Language :: Python :: 3 :: Only
Classifier: Topic :: Utilities
